CHANGES.txt
HACKING.txt
LICENSE.txt
MANIFEST.in
README.txt
setup.py
version.txt
src/restarter/__init__.py
src/restarter/app.py
src/restarter/cli.py
src/restarter/proc.py
src/restarter/service.py
src/restarter/test_proc.py
src/restarter/test_service.py
src/restarter.egg-info/PKG-INFO
src/restarter.egg-info/SOURCES.txt
src/restarter.egg-info/dependency_links.txt
src/restarter.egg-info/entry_points.txt
src/restarter.egg-info/not-zip-safe
src/restarter.egg-info/top_level.txt