Metadata-Version: 1.1
Name: restarter
Version: 0.4.4
Summary: Automatic service restart after updates
Home-page: https://bitbucket.org/flyingcircus/restarter
Author: Christian Kauhaus
Author-email: kc@gocept.com
License: ZPL
Platform: UNKNOWN
Classifier: Development Status :: 5 - Production/Stable
Classifier: Environment :: Console
Classifier: Intended Audience :: System Administrators
Classifier: License :: OSI Approved :: Zope Public License
Classifier: Operating System :: POSIX
Classifier: Programming Language :: Python :: 3
Classifier: Programming Language :: Python :: 3.2
Classifier: Programming Language :: Python :: 3.3
Classifier: Topic :: System :: Systems Administration
Classifier: Topic :: Utilities
